tudix/__init__.py
tudix/app.py
tudix-0.0.3.dist-info/METADATA
tudix-0.0.3.dist-info/WHEEL
tudix-0.0.3.dist-info/entry_points.txt
tudix-0.0.3.dist-info/top_level.txt
tudix-0.0.3.dist-info/RECORD
