Metadata-Version: 2.4
Name: tudix
Version: 0.0.3
Summary: Textual-based terminal text editor (experimental sibling of qudix).
Author: Sahil Pethe
License: Apache-2.0 OR MIT
Requires-Python: >=3.11
Requires-Dist: textual>=0.56.0
